prettypi/__init__.py
prettypi/pretty_print/__init__.py
prettypi/pretty_print/alert.py
prettypi/pretty_print/styled_str.py
prettypi/pretty_tree/__init__.py
prettypi/pretty_tree/pretty_tree.py
prettypi/pretty_tree/pretty_tree_path.py
prettypi/utils/__init__.py
prettypi/utils/ansi_codes.py
prettypi/utils/emojis.py
prettypi-0.3.3.dist-info/LICENSE
prettypi-0.3.3.dist-info/METADATA
prettypi-0.3.3.dist-info/WHEEL
prettypi-0.3.3.dist-info/top_level.txt
prettypi-0.3.3.dist-info/RECORD
