Metadata-Version: 2.1
Name: prettypi
Version: 0.3.3
Summary: A Python library for pretty printing and enhanced console output.
Home-page: https://github.com/Glawnn/PrettyPi
Author: Vodkas
Author-email: vodkas3630@gmail.com
License: MIT
Project-URL: Documentation, https://glawnn.github.io/PrettyPi/
Project-URL: Source, https://github.com/Glawnn/PrettyPi
Classifier: License :: OSI Approved :: MIT License
Classifier: Programming Language :: Python :: 3
Requires-Python: >=3.8
License-File: LICENSE
